bbo/__init__.py
bbo/dicts.py
bbo/exceptions.py
bbo/extractor_test.py
bbo/geometry.py
bbo/header.py
bbo/label_lib.py
bbo/path_management.py
bbo/spherical.py
bbo/test_geometry.py
bbo/vectorlib.py
bbo/yaml.py
bbo/optimization/__init__.py
bbo/optimization/best_trajectory.py
bbo/toolbox/__init__.py
bbo/toolbox/general.py
bbo/toolbox/interpolation.py
bbo/toolbox/plots.py
bbo_bbo-0.4.12.dist-info/METADATA
bbo_bbo-0.4.12.dist-info/WHEEL
bbo_bbo-0.4.12.dist-info/licenses/LICENSE
bbo_bbo-0.4.12.dist-info/RECORD
