Metadata-Version: 2.3
Name: bbo-bbo
Version: 0.4.12
Summary: Base tools for MPINB BBO group
Project-URL: Homepage, https://github.com/bbo-lab/bbo
Author-email: "BBO-lab @ caesar" <kay-michael.voit@caesar.de>
License: BSD-3-Clause
Classifier: License :: OSI Approved :: BSD License
Classifier: Programming Language :: Python :: 3.9
Classifier: Programming Language :: Python :: 3.10
Requires-Dist: numpy
Requires-Dist: pyyaml
Requires-Dist: scipy
